LICENSE.md
MANIFEST.in
README.md
setup.py
django_theme_soft_design.egg-info/PKG-INFO
django_theme_soft_design.egg-info/SOURCES.txt
django_theme_soft_design.egg-info/dependency_links.txt
django_theme_soft_design.egg-info/not-zip-safe
django_theme_soft_design.egg-info/top_level.txt
docs/blank.txt
theme_soft_design/__init__.py
theme_soft_design/admin.py
theme_soft_design/apps.py
theme_soft_design/forms.py
theme_soft_design/models.py
theme_soft_design/tests.py
theme_soft_design/urls.py
theme_soft_design/views.py
theme_soft_design/migrations/__init__.py
theme_soft_design/static/css/nucleo-icons.css
theme_soft_design/static/css/nucleo-svg.css
theme_soft_design/static/css/soft-design-system.css
theme_soft_design/static/css/soft-design-system.css.map
theme_soft_design/static/css/soft-design-system.min.css
theme_soft_design/static/fonts/nucleo-icons.eot
theme_soft_design/static/fonts/nucleo-icons.svg
theme_soft_design/static/fonts/nucleo-icons.ttf
theme_soft_design/static/fonts/nucleo-icons.woff
theme_soft_design/static/fonts/nucleo-icons.woff2
theme_soft_design/static/fonts/nucleo.eot
theme_soft_design/static/fonts/nucleo.ttf
theme_soft_design/static/fonts/nucleo.woff
theme_soft_design/static/fonts/nucleo.woff2
theme_soft_design/static/img/anastasia.jpg
theme_soft_design/static/img/annie-spratt.jpg
theme_soft_design/static/img/apple-icon.png
theme_soft_design/static/img/blog7-1.jpg
theme_soft_design/static/img/blog7-2.jpg
theme_soft_design/static/img/blog7-3.jpg
theme_soft_design/static/img/brooke.jpg
theme_soft_design/static/img/bruce-mars.jpg
theme_soft_design/static/img/card-2.jpg
theme_soft_design/static/img/card-3.jpg
theme_soft_design/static/img/charles.jpg
theme_soft_design/static/img/down-arrow-dark.svg
theme_soft_design/static/img/down-arrow-white.svg
theme_soft_design/static/img/down-arrow.svg
theme_soft_design/static/img/favicon.png
theme_soft_design/static/img/ivana-square.jpg
theme_soft_design/static/img/ivana.jpg
theme_soft_design/static/img/ivancik.jpg
theme_soft_design/static/img/jordan.jpg
theme_soft_design/static/img/kal-visuals-square.jpg
theme_soft_design/static/img/kal-visuals.jpg
theme_soft_design/static/img/marie.jpg
theme_soft_design/static/img/meeting.jpg
